openkosmos_ai/__init__.py
openkosmos_ai/ai_config.py
openkosmos_ai/common/model.py
openkosmos_ai/common/util.py
openkosmos_ai/nodes/__init__.py
openkosmos_ai/nodes/agent.py
openkosmos_ai/nodes/api.py
openkosmos_ai/nodes/base_node.py
openkosmos_ai/nodes/database_client.py
openkosmos_ai/nodes/dify_client.py
openkosmos_ai/nodes/git_repo.py
openkosmos_ai/nodes/openai_client.py
openkosmos_ai/nodes/placeholder.py
openkosmos_ai/nodes/rag_flow_client.py
openkosmos_ai/nodes/skill.py
openkosmos_ai/nodes/vector_store.py
openkosmos_ai/nodes/xinference_client.py
openkosmos_ai/nodes.py
openkosmos_ai/py.typed
openkosmos_ai-0.1.4.dist-info/WHEEL
openkosmos_ai-0.1.4.dist-info/METADATA
openkosmos_ai-0.1.4.dist-info/RECORD
