Metadata-Version: 2.3
Name: openkosmos-ai
Version: 0.1.4
Summary: openkosmos-ai
Author: wangtao
Author-email: wangtao <wangtao@openkosmos.com>
Requires-Dist: faiss-cpu>=1.13.2
Requires-Dist: gitpython>=3.1.46
Requires-Dist: langchain>=1.2.3
Requires-Dist: langchain-community>=0.4.1
Requires-Dist: langchain-huggingface>=1.1.3
Requires-Dist: langchain-openai>=1.1.7
Requires-Dist: langfuse>=3.11.2
Requires-Dist: langgraph>=1.0.5
Requires-Dist: openkosmos-core>=0.1.4
Requires-Dist: psycopg2-binary>=2.9.11
Requires-Dist: sqlalchemy>=2.0.44
Requires-Python: ==3.12.*
